mosaik_schedule_flocker/schedule_flocker/__init__.py
mosaik_schedule_flocker/schedule_flocker/core/__init__.py
mosaik_schedule_flocker/schedule_flocker/core/config.py
mosaik_schedule_flocker/schedule_flocker/core/generator.py
mosaik_schedule_flocker/schedule_flocker/core/util.py
mosaik_schedule_flocker/schedule_flocker/data/__init__.py
mosaik_schedule_flocker/schedule_flocker/data/get_mock_flocker_config_module.py
mosaik_schedule_flocker/schedule_flocker/model/__init__.py
mosaik_schedule_flocker/schedule_flocker/model/electricity_schedule.py
mosaik_schedule_flocker/schedule_flocker/model/electricity_value.py
mosaik_schedule_flocker/schedule_flocker/model/fill_electricity_schedule_dict_module.py
mosaik_schedule_flocker/schedule_flocker/mosaik/__init__.py
mosaik_schedule_flocker/schedule_flocker/mosaik/create/__init__.py
mosaik_schedule_flocker/schedule_flocker/mosaik/create/create_flocker_model_module.py
mosaik_schedule_flocker/schedule_flocker/mosaik/create/create_flocker_sink_model_module.py
mosaik_schedule_flocker/schedule_flocker/mosaik/create/create_flocker_source_model_module.py
mosaik_schedule_flocker/schedule_flocker/mosaik/flocker/__init__.py
mosaik_schedule_flocker/schedule_flocker/mosaik/flocker/flocker_meta.py
mosaik_schedule_flocker/schedule_flocker/mosaik/flocker/flocker_model.py
mosaik_schedule_flocker/schedule_flocker/mosaik/flocker/flocker_simulator.py
mosaik_schedule_flocker/schedule_flocker/mosaik/scenario/__init__.py
mosaik_schedule_flocker/schedule_flocker/mosaik/scenario/source_flocker_sink_scenario_module.py
mosaik_schedule_flocker/schedule_flocker/mosaik/sink/__init__.py
mosaik_schedule_flocker/schedule_flocker/mosaik/sink/flocker_sink_meta.py
mosaik_schedule_flocker/schedule_flocker/mosaik/sink/flocker_sink_model.py
mosaik_schedule_flocker/schedule_flocker/mosaik/sink/flocker_sink_simulator.py
mosaik_schedule_flocker/schedule_flocker/mosaik/source/__init__.py
mosaik_schedule_flocker/schedule_flocker/mosaik/source/flocker_source_meta.py
mosaik.Schedule_Flocker-0.1.0rc20220724000630.dist-info/METADATA
mosaik.Schedule_Flocker-0.1.0rc20220724000630.dist-info/WHEEL
mosaik.Schedule_Flocker-0.1.0rc20220724000630.dist-info/top_level.txt
mosaik.Schedule_Flocker-0.1.0rc20220724000630.dist-info/RECORD
